data_quality_tool/__init__.py
data_quality_tool/__main__.py
data_quality_tool/quality_check.py
wwl_toc_data_quality_tool-0.1.1.dist-info/LICENSE
wwl_toc_data_quality_tool-0.1.1.dist-info/METADATA
wwl_toc_data_quality_tool-0.1.1.dist-info/WHEEL
wwl_toc_data_quality_tool-0.1.1.dist-info/entry_points.txt
wwl_toc_data_quality_tool-0.1.1.dist-info/top_level.txt
wwl_toc_data_quality_tool-0.1.1.dist-info/RECORD
