Metadata-Version: 2.1
Name: wwl_toc_data_quality_tool
Version: 0.1.1
Summary: A tool to check data quality against predefined standards.
Author-email: "Xifan.Z" <xifanzou42@gmail.com>
License: Apache License
Project-URL: Homepage, https://github.com/xifanzou/data_quality_check
Classifier: Programming Language :: Python :: 3
Classifier: Operating System :: OS Independent
Requires-Python: >=3.6
License-File: LICENSE
Requires-Dist: pandas
